{"9lMPSxOAOdNISDvDPbfyyg==":"sw_2019-05-18_prediction_overlay2-1024x1145.png","U8RxDI7suC5uRAFRF3+d2A==":"sw_2019-05-18_prediction_overlay2-1-1024x1145.png","jNVTAv5s/7q7DikwVkxXpQ==":"s2-1024x756.png","rW85tji2eBa790CYZMXyFw==":"sw_2019-05-18_prediction_overlay2-576x563.png","wCgIwS6yxsqJeogmpsSZcg==":"deepeo_demo_web-952x1064.png","p4GCyxzErMZLcIy4CfVrBQ==":"deepeo_demo_clean-1024x1145.png","63/735ib9oyu6bJeX2Eh4g==":"deepeo_demo_clean-468x523.png","tKYBilEiv3ILeU0ne/jFIg==":"deepeo_demo_clean-1-468x523.png","Vjp8YX9vJjAzimRyboEjOQ==":"deepeo_demo_clean-2000x2236.png","3i4fbnzbTceV4lF5/aN7wg==":"deepeo_demo_clean-1-2000x2236.png","JZVyeyXX2tF3CW78nsu7eQ==":"deepeo-1024x1024.png","rNK+ZERUWtB5Tdjb9ARfDg==":"deepeo-1-1024x1024.png","5iH5RtHdn1m60LmKDTYsEQ==":"deepeo-2-1024x1024.png","XDEW6ZCSzj8UjzolCm4pEw==":"deepeo-3-1024x1024.png","OT8cIK9p8FDIhaUBZ/ZY6A==":"background-2000x967.png","zyfXSSMf5q9zL5dBaRD9OA==":"clearsky-1024x341.png","Y7ud/eEdg0CD56qgiYHAAw==":"clearsky-1-1024x341.png","nzRO8hIKY0GsNe7UzNw14w==":"clearsky-1728x576.png","TA4VFiBl8GpgGMZhC7BUYQ==":"mbr-492x277.jpg","Oq+oTovcgYxZMR+ZLIx8mA==":"mbr-492x328.jpg","TgLCnB/T5QjoTUJlLFz+Bg==":"mbr-1-492x328.jpg","i1RSklAAkw4QDPzgixToiQ==":"mbr-2-492x328.jpg","FmWbdKQSlBoWJHRuXkRCKA==":"mbr-3-492x328.jpg"}